cosimtlk/__about__.py
cosimtlk/__init__.py
cosimtlk/_fmu.py
cosimtlk/cli.py
cosimtlk/client.py
cosimtlk/models.py
cosimtlk/py.typed
cosimtlk/app/__init__.py
cosimtlk/app/client.py
cosimtlk/app/config.py
cosimtlk/app/dependencies.py
cosimtlk/app/main.py
cosimtlk/app/schemas.py
cosimtlk/app/routers/__init__.py
cosimtlk/app/routers/fmus.py
cosimtlk/app/routers/simulators.py
cosimtlk/app/services/__init__.py
cosimtlk/app/services/simulator.py
cosimtlk/simulation/__init__.py
cosimtlk/simulation/environment.py
cosimtlk/simulation/simulator.py
cosimtlk/simulation/state.py
cosimtlk/simulation/storage.py
cosimtlk/simulation/utils.py
cosimtlk/simulation/entities/__init__.py
cosimtlk/simulation/entities/base.py
cosimtlk/simulation/entities/fmu.py
cosimtlk/simulation/entities/generic.py
cosimtlk/simulation/entities/input.py
cosimtlk/simulation/entities/source.py
cosimtlk/simulation/entities/stateobserver.py
cosimtlk-0.6.8.dist-info/METADATA
cosimtlk-0.6.8.dist-info/WHEEL
cosimtlk-0.6.8.dist-info/entry_points.txt
cosimtlk-0.6.8.dist-info/licenses/LICENCE
cosimtlk-0.6.8.dist-info/RECORD
